Workbook

Sheet 8-Week Roadmap
A1: Cloud-Menu: 8-Week Agile Implementation Roadmap
A2: Kickoff date (Monday of Week 1): | C2: 46328 | D2: INPUT (assumed date, change to the real kickoff). Start/End dates below recalculate. Check festive-season (December) trading peaks when fixing go-live.
A4: Sprint | B4: Start wk | C4: End wk | D4: Start (Mon) | E4: End (Fri) | F4: Workstream | G4: Deliverable / milestone | H4: Stories | I4: Owner role | J4: Exit criterion
A5: Setup | B5: 0 | C5: 0 | D5: =$C$2+(B5-1)*7 -> 46321 | E5: =$C$2+(C5-1)*7+4 -> 46325 | F5: Product | G5: Aggregator shortlist and sandbox access requested; venue interviews (5-8 per persona); counts of candidate venues | H5: - | I5: Founder / PO | J5: Aggregator chosen; interview insights fed into backlog
A6: Setup | B6: 0 | C6: 0 | D6: =$C$2+(B6-1)*7 -> 46321 | E6: =$C$2+(C6-1)*7+4 -> 46325 | F6: Engineering | G6: Repo and monorepo, CI/CD with Lighthouse budget, Terraform base, staging environment, observability skeleton | H6: - | I6: Tech Lead | J6: Hello-world deploys to staging through CI
A7: Setup | B7: 0 | C7: 0 | D7: =$C$2+(B7-1)*7 -> 46321 | E7: =$C$2+(C7-1)*7+4 -> 46325 | F7: Design | G7: Mobile-first design system, wireframes for Screens A-C, EN/SW copy deck | H7: - | I7: Designer | J7: Design review signed by PO
A8: S1 | B8: 1 | C8: 2 | D8: =$C$2+(B8-1)*7 -> 46328 | E8: =$C$2+(C8-1)*7+4 -> 46339 | F8: Platform | G8: DB schema migrations, staff auth with roles, venue/table models, QR generation and signed tokens | H8: US-506, US-602 | I8: Backend | J8: QR PDF printed and scanned on 3 device types
A9: S1 | B9: 1 | C9: 2 | D9: =$C$2+(B9-1)*7 -> 46328 | E9: =$C$2+(C9-1)*7+4 -> 46339 | F9: Guest app | G9: Session init and participants, menu browse, modifiers, cart, order submit (idempotent) | H9: US-101, US-102, US-201, US-202, US-203, US-204 | I9: Full-stack | J9: Scan QR, order, order stored (staging)
A10: S1 | B10: 1 | C10: 2 | D10: =$C$2+(B10-1)*7 -> 46328 | E10: =$C$2+(C10-1)*7+4 -> 46339 | F10: Venue admin | G10: Menu CRUD with image optimisation and CSV import | H10: US-601 | I10: Full-stack | J10: Pilot menu loaded in under 1 hour
A11: S1 | B11: 1 | C11: 2 | D11: =$C$2+(B11-1)*7 -> 46328 | E11: =$C$2+(C11-1)*7+4 -> 46339 | F11: Performance | G11: PWA shell, service worker, bundle budget enforced in CI | H11: US-701 | I11: Front-end | J11: LCP at most 4.0 s on Fast 3G profile
A12: S1 | B12: 2 | C12: 2 | D12: =$C$2+(B12-1)*7 -> 46335 | E12: =$C$2+(C12-1)*7+4 -> 46339 | F12: Milestone | G12: M1: Ordering core demoable in staging | I12: Team | J12: Sprint 1 review: ticket data visible via API
A13: S2 | B13: 3 | C13: 4 | D13: =$C$2+(B13-1)*7 -> 46342 | E13: =$C$2+(C13-1)*7+4 -> 46353 | F13: Staff app | G13: KDS ticket queue and state changes, waiter dashboard (tables, balances), real-time channels (SSE and WebSocket) | H13: US-501, US-502, US-504 | I13: Full-stack | J13: Order-to-ticket p95 at most 2 s in staging
A14: S2 | B14: 3 | C14: 4 | D14: =$C$2+(B14-1)*7 -> 46342 | E14: =$C$2+(C14-1)*7+4 -> 46353 | F14: Billing | G14: Bill view, equal split, itemized split with claims, split lock with expiry and concurrency control | H14: US-301, US-302, US-303, US-305 | I14: Backend + Front-end | J14: All Gherkin split scenarios automated and green
A15: S2 | B15: 3 | C15: 4 | D15: =$C$2+(B15-1)*7 -> 46342 | E15: =$C$2+(C15-1)*7+4 -> 46353 | F15: Payments | G15: Aggregator integration in sandbox: push initiation, idempotency, payment states | H15: US-401 | I15: Backend | J15: Sandbox payment succeeds for each wallet
A16: S2 | B16: 4 | C16: 4 | D16: =$C$2+(B16-1)*7 -> 46349 | E16: =$C$2+(C16-1)*7+4 -> 46353 | F16: Milestone | G16: M2: Split and pay in sandbox, end to end | I16: Team | J16: Demo: 3 guests split and pay in sandbox, ticket on KDS
A17: S3 | B17: 5 | C17: 6 | D17: =$C$2+(B17-1)*7 -> 46356 | E17: =$C$2+(C17-1)*7+4 -> 46367 | F17: Payments | G17: Webhooks (signature, dedupe, async processing), failure and retry flows, reconciliation job, late-success handling | H17: US-402, US-403, US-404, US-407 | I17: Backend | J17: Chaos test: dropped/duplicated callbacks reconcile correctly
A18: S3 | B18: 5 | C18: 6 | D18: =$C$2+(B18-1)*7 -> 46356 | E18: =$C$2+(C18-1)*7+4 -> 46367 | F18: Guest app | G18: Order status tracking, sold-out sync, digital receipts | H18: US-205, US-206, US-405 | I18: Full-stack | J18: Receipt generated for every successful payment
A19: S3 | B19: 5 | C19: 6 | D19: =$C$2+(B19-1)*7 -> 46356 | E19: =$C$2+(C19-1)*7+4 -> 46367 | F19: Resilience | G19: Reconnect and resync, offline banners, polling fallback; rate limiting and security hardening; metrics and alerts | H19: US-505, US-702, US-703 | I19: Tech Lead | J19: Network-drop test passes; alerts fire in drill
A20: S3 | B20: 5 | C20: 6 | D20: =$C$2+(B20-1)*7 -> 46356 | E20: =$C$2+(C20-1)*7+4 -> 46367 | F20: Quality | G20: Load test (target 9,000 connections), live-money test with small amounts, pen-test checklist, device matrix pass | H20: - | I20: QA | J20: No open critical/high defects
A21: S3 | B21: 6 | C21: 6 | D21: =$C$2+(B21-1)*7 -> 46363 | E21: =$C$2+(C21-1)*7+4 -> 46367 | F21: Milestone | G21: M3: Pilot readiness review (go/no-go for beta) | I21: Founder + Tech Lead | J21: Readiness checklist complete
A22: S4 | B22: 7 | C22: 8 | D22: =$C$2+(B22-1)*7 -> 46370 | E22: =$C$2+(C22-1)*7+4 -> 46381 | F22: Operations | G22: Session lifecycle, cash payment recording, station routing, call waiter, tipping | H22: US-103, US-104, US-406, US-503, US-207, US-306 | I22: Full-stack | J22: Waiter can resolve unpaid-share cases without engineering
A23: S4 | B23: 7 | C23: 8 | D23: =$C$2+(B23-1)*7 -> 46370 | E23: =$C$2+(C23-1)*7+4 -> 46381 | F23: Venue admin | G23: Daily sales summary and export, venue sign-up and subscription, shared items | H23: US-603, US-604, US-304 | I23: Full-stack | J23: Manager reconciles a day in under 10 minutes
A24: S4 | B24: 7 | C24: 8 | D24: =$C$2+(B24-1)*7 -> 46370 | E24: =$C$2+(C24-1)*7+4 -> 46381 | F24: Launch | G24: Pilot onboarding playbook, venue training (30 min), QR sticker installation, support rota for first weekends, feedback loop | H24: - | I24: Founder / Support | J24: First 5-10 pilot venues live
A25: S4 | B25: 8 | C25: 8 | D25: =$C$2+(B25-1)*7 -> 46377 | E25: =$C$2+(C25-1)*7+4 -> 46381 | F25: Milestone | G25: M4: MVP beta launch | I25: Team | J25: Pilot KPIs dashboard live; hypercare started
A27: Notes
A28: - Week 0 is pre-sprint setup (about one week before Week 1); Start date for week 0 falls one week before kickoff.
A29: - Sprint cadence: planning (Mon), daily stand-up, mid-sprint refinement, review and retro (Fri of week 2). Definition of Ready/Done in 02_Product_Backlog.xlsx.
A30: - Scope flex: S4 holds Should/Could stories; cut them first if S1-S3 slip. Must-have path is complete at the end of S3.
A31: - Story IDs refer to the Backlog sheet in 02_Product_Backlog.xlsx.

Sheet Sprint Goals
A1: Sprint | B1: Weeks | C1: Sprint goal | D1: Demo at review | E1: Key risks to watch
A2: S1 | B2: 1-2 | C2: A guest can scan a table QR, browse a fast menu, customise and submit an order that is stored and visible via API. | D2: Live scan on a mid-range phone over 4G; order appears in the database/API; QR sticker sheet printed. | E2: R03 performance on weak networks; R16 team capacity
A3: S2 | B3: 3-4 | C3: Staff see tickets in real time, guests can split the bill and start a sandbox mobile money payment. | D3: Three phones: order, KDS ticket, split, sandbox payment. | E3: R01 callbacks; R02 aggregator sandbox quality; R08 split concurrency
A4: S3 | B4: 5-6 | C4: Payments are production-grade (webhooks, retries, reconciliation) and the system survives network drops. | D4: Fault-injection demo: kill callbacks, drop Wi-Fi, replay events; live small-amount payments. | E4: R01, R04, R10 duplicate payments
A5: S4 | B5: 7-8 | C5: Pilot venues are live with training, support and reporting; beta feedback loop running. | D5: First real venue service; KPI dashboard. | E5: R06 adoption; R12 support load; R15 festive-season timing

Sheet Risk Matrix
A1: Risk Assessment & Mitigation Matrix
A2: Probability and Impact are 1-5 (blue cells are editable inputs). Score = P x I. Rating: Critical >= 15, High 10-14, Medium 5-9, Low < 5.
A4: ID | B4: Category | C4: Risk | D4: Cause / trigger | E4: P (1-5) | F4: I (1-5) | G4: Score | H4: Rating | I4: Mitigation (preventive) | J4: Contingency (if it happens) | K4: Owner | L4: Early-warning indicator | M4: Status
A5: R01 | B5: Technical | C5: Failed or delayed payment callbacks leave paid shares showing unpaid | D5: Aggregator outage, network failure, our endpoint down, bad signature handling | E5: 4 | F5: 5 | G5: =E5*F5 -> 20 | H5: =IF(G5>=15,"Critical",IF(G5>=10,"High",IF(G5>=5,"Medium","Low"))) -> Critical | I5: Persist raw webhook before processing; respond 200 fast; async worker; reconciliation polling for PENDING > 3 min; idempotent transitions; alert on pending age > 10 min; synthetic callback tests in staging. | J5: Waiter dashboard shows "verify payment" with provider reference lookup; manual mark-paid with audit log; daily reconciliation report. | K5: Tech Lead | L5: Pending payments older than 5 min; webhook lag p95 | M5: Open
A6: R02 | B6: Technical | C6: Mobile money push prompts not delivered or aggregator downtime | D6: Provider USSD/STK issues, aggregator maintenance, network congestion on peak nights | E6: 3 | F6: 5 | G6: =E6*F6 -> 15 | H6: =IF(G6>=15,"Critical",IF(G6>=10,"High",IF(G6>=5,"Medium","Low"))) -> Critical | I6: Contract SLA and status page; retry with backoff and resend-prompt button; alternate provider path in architecture (adapter interface); health probes and alerting. | J6: Offer cash recorded by waiter; announce degraded mode on staff screens; switch to backup aggregator if contracted. | K6: Tech Lead / Founder | L6: Initiation failure rate above 5% in 10 min | M6: Open
A7: R03 | B7: Technical | C7: Slow loads and timeouts on 3G/4G and mid-range phones lead to abandonment | D7: Heavy bundles, large images, high latency to hosting region, congested venue networks | E7: 4 | F7: 4 | G7: =E7*F7 -> 16 | H7: =IF(G7>=15,"Critical",IF(G7>=10,"High",IF(G7>=5,"Medium","Low"))) -> Critical | I7: Performance budget in CI (JS <= 150 KB gz, LCP targets); image variants via CDN; service worker caching; region latency test in Week 1; skeleton screens; menu cache with ETag. | J7: Lite mode (text-only menu); move hosting region or add CDN rules; hotfix bundle regressions. | K7: Front-end Lead | L7: RUM LCP p75 above budget; scan-to-menu failures | M7: Open
A8: R04 | B8: Operational | C8: Venue Wi-Fi drops make KDS/waiter views stale (offline kitchen state) | D8: Weak routers, shared Wi-Fi, power cuts | E8: 4 | F8: 4 | G8: =E8*F8 -> 16 | H8: =IF(G8>=15,"Critical",IF(G8>=10,"High",IF(G8>=5,"Medium","Low"))) -> Critical | I8: Auto-reconnect with seq resync; offline banner; polling fallback; staff devices can use mobile data hotspot; recommend dedicated router in onboarding checklist; optional printed ticket fallback (post-MVP). | J8: Revert to verbal/paper ordering for the affected shift; staff manually refresh; support call-out. | K8: Support Lead | L8: Staff-device disconnect rate; reconnect time p95 | M8: Open
A9: R05 | B9: Business | C9: Regulatory and tax obligations (fiscal receipts, personal data, payment licensing) block launch or add scope | D9: Venues must issue fiscal receipts; platform may be seen as handling funds; data protection law | E9: 3 | F9: 5 | G9: =E9*F9 -> 15 | H9: =IF(G9>=15,"Critical",IF(G9>=10,"High",IF(G9>=5,"Medium","Low"))) -> Critical | I9: Early advice from a local tax/legal adviser (Week 1); use licensed aggregator with direct settlement to venues; privacy notice and minimal data; clarify EFD/VFD handling and integrate or instruct venues. | J9: Limit pilot to compliant venues; add fiscal integration as a priority story; delay launch rather than operate non-compliant. | K9: Founder | L9: Adviser feedback; venue questions on receipts | M9: Open
A10: R06 | B10: Business | C10: Low venue adoption or staff resistance | D10: Perceived complexity, fear of losing tips, owner distrust of new tools | E10: 3 | F10: 4 | G10: =E10*F10 -> 12 | H10: =IF(G10>=15,"Critical",IF(G10>=10,"High",IF(G10>=5,"Medium","Low"))) -> High | I10: Co-design with pilot venues; show tip protection (guest can add tip); 30-minute training; waiter-first features; visible owner dashboard; free pilot period with success criteria. | J10: Adjust workflow after feedback; on-site support for first 2 weekends; switch to higher-fit venues. | K10: Founder | L10: QR order share below 30% in week 2 | M10: Open
A11: R07 | B11: Technical | C11: Real-time layer degrades under peak load (Friday/Saturday nights) | D11: Too many connections per node, Redis saturation, slow database queries | E11: 2 | F11: 4 | G11: =E11*F11 -> 8 | H11: =IF(G11>=15,"Critical",IF(G11>=10,"High",IF(G11>=5,"Medium","Low"))) -> Medium | I11: Load test before beta (9,000 connections); horizontal scaling; connection limits; efficient event payloads; DB indexes; autoscaling alarms. | J11: Fallback to polling; scale out nodes; shed non-critical events. | K11: Tech Lead | L11: Event delivery p95 above 2 s; CPU > 70% | M11: Open
A12: R08 | B12: Technical | C12: Split race conditions create wrong shares or double claims | D12: Concurrent edits by guests; late orders while splitting | E12: 3 | F12: 4 | G12: =E12*F12 -> 12 | H12: =IF(G12>=15,"Critical",IF(G12>=10,"High",IF(G12>=5,"Medium","Low"))) -> High | I12: Row lock on split; bill_version check; unique constraints; deterministic rounding; extensive Gherkin-based automated tests; property-based tests for rounding. | J12: Waiter can void/reopen split; refund process for overpayment; audit log. | K12: Backend Lead | L12: Split recalculation conflicts (409) rate | M12: Open
A13: R09 | B13: Operational | C13: Fake or prank orders from people not at the table | D13: Photographed or shared QR codes; no seat verification | E13: 3 | F13: 3 | G13: =E13*F13 -> 9 | H13: =IF(G13>=15,"Critical",IF(G13>=10,"High",IF(G13>=5,"Medium","Low"))) -> Medium | I13: Signed, rotatable QR; rate limits; waiter confirmation mode for new sessions at risk venues; unusual-order flags; table-level geofencing is NOT relied on (GPS unreliable indoors). | J13: Waiter cancels order; rotate QR; block session. | K13: Product Owner | L13: Cancelled-by-waiter rate | M13: Open
A14: R10 | B14: Technical | C14: Duplicate or wrong payments (double tap, retries, wrong phone number) | D14: Network retries, guest enters someone else’s number | E14: 2 | F14: 5 | G14: =E14*F14 -> 10 | H14: =IF(G14>=15,"Critical",IF(G14>=10,"High",IF(G14>=5,"Medium","Low"))) -> High | I14: Idempotency keys; one in-flight attempt per share (unique index); clear phone confirmation; amount shown on prompt; refund workflow documented with aggregator. | J14: Manual refund via aggregator; flag needs_review; customer support script. | K14: Backend Lead | L14: Payments with needs_review flag | M14: Open
A15: R11 | B15: Operational | C15: Guests leave without paying (partial settlement) | D15: Group members leave; reluctance to pay | E15: 3 | F15: 3 | G15: =E15*F15 -> 9 | H15: =IF(G15>=15,"Critical",IF(G15>=10,"High",IF(G15>=5,"Medium","Low"))) -> Medium | I15: Shares clearly visible to waiter; reminders; reassign unpaid share to others; cash fallback; encourage paying before leaving via prompts. | J15: Waiter records outstanding amount; venue policy applies. | K15: Product Owner | L15: Unsettled tables at close | M15: Open
A16: R12 | B16: Operational | C16: Support overload on peak nights | D16: New venues, training gaps, issues arriving simultaneously | E16: 3 | F16: 4 | G16: =E16*F16 -> 12 | H16: =IF(G16>=15,"Critical",IF(G16>=10,"High",IF(G16>=5,"Medium","Low"))) -> High | I16: Support rota for Fri/Sat; WhatsApp support line; in-app help; runbooks; staggered venue onboarding (max 3 per week). | J16: Pause new onboarding; escalate to engineering on-call. | K16: Support Lead | L16: Open tickets older than 30 min on peak nights | M16: Open
... A22: R18 | B22: Technical | C22: Device and browser fragmentation breaks UI on older phones | D22: Old Android WebView, low memory devices | E22: 3 | F22: 3 | G22: =E22*F22 -> 9 | H22: =IF(G22>=15,"Critical",IF(G22>=10,"High",IF(G22>=5,"Medium","Low"))) -> Medium | I22: Device matrix with low-end Android; progressive enhancement; avoid heavy libraries; Sentry on real devices. | J22: Hotfix and targeted polyfills; lite mode. | K22: QA | L22: Errors by browser/device in RUM | M22: Open

Sheet Heat Map
A1: Risk heat map: number of risks by Probability (rows) and Impact (columns)
A3: P \ I | B3: 1 | C3: 2 | D3: 3 | E3: 4 | F3: 5
A4: 5 | B4: =COUNTIFS('Risk Matrix'!$E$5:$E$200,$A4,'Risk Matrix'!$F$5:$F$200,B$3) -> 0 | C4: =COUNTIFS('Risk Matrix'!$E$5:$E$200,$A4,'Risk Matrix'!$F$5:$F$200,C$3) -> 0 | D4: =COUNTIFS('Risk Matrix'!$E$5:$E$200,$A4,'Risk Matrix'!$F$5:$F$200,D$3) -> 0 | E4: =COUNTIFS('Risk Matrix'!$E$5:$E$200,$A4,'Risk Matrix'!$F$5:$F$200,E$3) -> 0 | F4: =COUNTIFS('Risk Matrix'!$E$5:$E$200,$A4,'Risk Matrix'!$F$5:$F$200,F$3) -> 0
A5: 4 | B5: =COUNTIFS('Risk Matrix'!$E$5:$E$200,$A5,'Risk Matrix'!$F$5:$F$200,B$3) -> 0 | C5: =COUNTIFS('Risk Matrix'!$E$5:$E$200,$A5,'Risk Matrix'!$F$5:$F$200,C$3) -> 0 | D5: =COUNTIFS('Risk Matrix'!$E$5:$E$200,$A5,'Risk Matrix'!$F$5:$F$200,D$3) -> 0 | E5: =COUNTIFS('Risk Matrix'!$E$5:$E$200,$A5,'Risk Matrix'!$F$5:$F$200,E$3) -> 2 | F5: =COUNTIFS('Risk Matrix'!$E$5:$E$200,$A5,'Risk Matrix'!$F$5:$F$200,F$3) -> 1
A6: 3 | B6: =COUNTIFS('Risk Matrix'!$E$5:$E$200,$A6,'Risk Matrix'!$F$5:$F$200,B$3) -> 0 | C6: =COUNTIFS('Risk Matrix'!$E$5:$E$200,$A6,'Risk Matrix'!$F$5:$F$200,C$3) -> 0 | D6: =COUNTIFS('Risk Matrix'!$E$5:$E$200,$A6,'Risk Matrix'!$F$5:$F$200,D$3) -> 4 | E6: =COUNTIFS('Risk Matrix'!$E$5:$E$200,$A6,'Risk Matrix'!$F$5:$F$200,E$3) -> 6 | F6: =COUNTIFS('Risk Matrix'!$E$5:$E$200,$A6,'Risk Matrix'!$F$5:$F$200,F$3) -> 2
A7: 2 | B7: =COUNTIFS('Risk Matrix'!$E$5:$E$200,$A7,'Risk Matrix'!$F$5:$F$200,B$3) -> 0 | C7: =COUNTIFS('Risk Matrix'!$E$5:$E$200,$A7,'Risk Matrix'!$F$5:$F$200,C$3) -> 0 | D7: =COUNTIFS('Risk Matrix'!$E$5:$E$200,$A7,'Risk Matrix'!$F$5:$F$200,D$3) -> 0 | E7: =COUNTIFS('Risk Matrix'!$E$5:$E$200,$A7,'Risk Matrix'!$F$5:$F$200,E$3) -> 1 | F7: =COUNTIFS('Risk Matrix'!$E$5:$E$200,$A7,'Risk Matrix'!$F$5:$F$200,F$3) -> 2
A8: 1 | B8: =COUNTIFS('Risk Matrix'!$E$5:$E$200,$A8,'Risk Matrix'!$F$5:$F$200,B$3) -> 0 | C8: =COUNTIFS('Risk Matrix'!$E$5:$E$200,$A8,'Risk Matrix'!$F$5:$F$200,C$3) -> 0 | D8: =COUNTIFS('Risk Matrix'!$E$5:$E$200,$A8,'Risk Matrix'!$F$5:$F$200,D$3) -> 0 | E8: =COUNTIFS('Risk Matrix'!$E$5:$E$200,$A8,'Risk Matrix'!$F$5:$F$200,E$3) -> 0 | F8: =COUNTIFS('Risk Matrix'!$E$5:$E$200,$A8,'Risk Matrix'!$F$5:$F$200,F$3) -> 0
A10: Totals by rating
A11: Critical | B11: =COUNTIF('Risk Matrix'!$H$5:$H$200,A11) -> 5
A12: High | B12: =COUNTIF('Risk Matrix'!$H$5:$H$200,A12) -> 8
A13: Medium | B13: =COUNTIF('Risk Matrix'!$H$5:$H$200,A13) -> 5
A14: Low | B14: =COUNTIF('Risk Matrix'!$H$5:$H$200,A14) -> 0
A15: Total | B15: =SUM(B11:B14) -> 18
