Workbook

Sheet README
A1: Cloud-Menu: Product Backlog & Definitions of Ready/Done
A3: Version | B3: 0.1 draft, 21 Oct 2026
A4: Sheets | B4: Epics, Backlog (stories with Gherkin acceptance criteria), Sprint Summary (formula-driven), Definition of Ready, Definition of Done
A5: Priority | B5: MoSCoW (Must / Should / Could). Rank is the order of delivery within the backlog.
A6: Story points | B6: Fibonacci estimates are initial planning guesses to be re-estimated in planning sessions. Edit the Points and Sprint columns; the Sprint Summary recalculates.
A7: Currency | B7: All money is in TZS (whole shillings). Example values in acceptance criteria are illustrative.
A8: Sprints | B8: S1 = Weeks 1-2, S2 = Weeks 3-4, S3 = Weeks 5-6, S4 = Weeks 7-8 (MVP beta launch at the end of S4). Week 0 is pre-sprint setup.
A9: Editable cells | B9: Backlog columns G (Points) and H (Sprint) feed the Sprint Summary. Status (column K) is a dropdown.

Sheet Epics
A1: Epic ID | B1: Epic | C1: Description | D1: Priority | E1: Stories | F1: Points
A2: E1 | B2: Table QR & Session Binding | C2: Guests reach the right table session by scanning a QR code, with no sign-up. | D2: Must | E2: =COUNTIF(Backlog!$B$2:$B$200,A2) -> 4 | F2: =SUMIFS(Backlog!$G$2:$G$200,Backlog!$B$2:$B$200,A2) -> 14
A3: E2 | B3: Menu, Modifiers & Ordering | C3: Browse, customise and submit orders in real time from a fast PWA. | D3: Must | E3: =COUNTIF(Backlog!$B$2:$B$200,A3) -> 7 | F3: =SUMIFS(Backlog!$G$2:$G$200,Backlog!$B$2:$B$200,A3) -> 32
A4: E3 | B4: Bill-Splitting Engine | C4: Equal and itemized splitting with deterministic rounding and locking. | D4: Must | E4: =COUNTIF(Backlog!$B$2:$B$200,A4) -> 6 | F4: =SUMIFS(Backlog!$G$2:$G$200,Backlog!$B$2:$B$200,A4) -> 34
A5: E4 | B5: Mobile Money Payments | C5: Push-prompt payments, webhook-driven state, reconciliation, receipts. | D5: Must | E5: =COUNTIF(Backlog!$B$2:$B$200,A5) -> 7 | F5: =SUMIFS(Backlog!$G$2:$G$200,Backlog!$B$2:$B$200,A5) -> 42
A6: E5 | B6: KDS & Waiter Dashboard | C6: Real-time ticket management and table/payment visibility for staff. | D6: Must | E6: =COUNTIF(Backlog!$B$2:$B$200,A6) -> 6 | F6: =SUMIFS(Backlog!$G$2:$G$200,Backlog!$B$2:$B$200,A6) -> 42
A7: E6 | B7: Venue Admin & Onboarding | C7: Menu management, table/QR generation, reporting, subscription. | D7: Should | E7: =COUNTIF(Backlog!$B$2:$B$200,A7) -> 4 | F7: =SUMIFS(Backlog!$G$2:$G$200,Backlog!$B$2:$B$200,A7) -> 23
A8: E7 | B8: Platform, Performance & Security | C8: Performance budgets, observability, abuse protection. | D8: Must | E8: =COUNTIF(Backlog!$B$2:$B$200,A8) -> 3 | F8: =SUMIFS(Backlog!$G$2:$G$200,Backlog!$B$2:$B$200,A8) -> 15
D9: Total | E9: =SUM(E2:E8) -> 37 | F9: =SUM(F2:F8) -> 202

Sheet Backlog
A1: ID | B1: Epic | C1: Priority | D1: Rank | E1: Persona | F1: User Story | G1: Points | H1: Sprint | I1: Dependencies | J1: Acceptance Criteria (Gherkin) | K1: Status
A2: US-101 | B2: E1 | C2: Must | D2: 1 | E2: Lounge Guest | F2: As a Lounge Guest, I want to scan the QR code on my table and land on that venue’s menu with my table already selected so that I can order immediately without installing an app or signing up. | G2: 5 | H2: S1 | J2: Scenario: First scan opens a new table session Given table "T12" at venue "Masaki Lounge" has no active session And the QR code encodes a signed table token When a guest opens the QR URL in a mobile browser Then the system creates an active table session bound to "T12" And the guest receives a session token valid for that session only And the menu page is shown without any sign-up prompt Scenario: Tampered or unknown QR token is rejected Given a QR URL whose token signature is invalid When the guest opens the URL Then the API responds 404 or 422 with a problem+json body And the guest sees "This QR code is not valid. Please ask your waiter." Scenario: Venue is inactive Given venue "Masaki Lounge" subscription status is "SUSPENDED" When a guest scans a table QR code Then the guest sees a friendly "Digital ordering unavailable" page And no session is created | K2: Not started
A3: US-102 | B3: E1 | C3: Must | D3: 2 | E3: Lounge Guest | F3: As a Lounge Guest, I want to join the table session already opened by a friend so that all of us order and pay against one shared table bill. | G3: 3 | H3: S1 | I3: US-101 | J3: Scenario: Second guest joins existing session Given table "T12" has an active session with 1 participant When another device scans the same QR code Then the device is added as a new participant to the same session And a default display name such as "Guest 2" is assigned And the guest can later edit the display name Scenario: Same device re-scans Given a device already has a participant record in the session When it scans the QR code again Then no duplicate participant is created And the existing session token is reused Scenario: Participant limit Given a session has 20 participants When a 21st device scans the QR code Then the guest is asked to see a waiter And the session is unchanged | K3: Not started
A4: US-201 | B4: E2 | C4: Must | D4: 3 | E4: Lounge Guest | F4: As a Lounge Guest, I want to browse the menu by category and search items so that I can find what I want quickly on a slow connection. | G4: 8 | H4: S1 | J4: Scenario: Menu loads fast on throttled 4G Given a mid-range Android device with Fast 4G throttling When the guest opens the menu page Then Largest Contentful Paint is at most 2.5 seconds at p75 And initial JavaScript is at most 150 KB gzipped Scenario: Category navigation Given the menu has categories "Drinks", "Grill" and "Snacks" When the guest taps "Grill" Then the list scrolls to "Grill" items with name, price in TZS and photo Scenario: Unavailable items are clearly shown Given item "Grilled Tilapia" is marked unavailable When the guest views the menu Then the item is greyed out with "Sold out" and cannot be added to the cart | K4: Not started
A5: US-202 | B5: E2 | C5: Must | D5: 4 | E5: Lounge Guest | F5: As a Lounge Guest, I want to choose modifiers such as mixers and spice level so that my order is prepared exactly as I want. | G5: 5 | H5: S1 | I5: US-201 | J5: Scenario: Required modifier group must be chosen Given item "Vodka" has required group "Mixer" (min 1, max 1) When the guest taps "Add to cart" without choosing a mixer Then the add action is blocked And "Choose a mixer" is shown Scenario: Modifier price adjusts item price Given modifier "Double shot" has price delta +3,000 TZS When the guest selects it on a 8,000 TZS item Then the line price shows 11,000 TZS before quantity Scenario: Max selections enforced Given group "Extras" allows at most 2 selections When the guest selects a third extra Then the selection is rejected with a message | K5: Not started
A6: US-203 | B6: E2 | C6: Must | D6: 5 | E6: Lounge Guest | F6: As a Lounge Guest, I want to review and edit my cart with quantities and notes so that I avoid mistakes before I send the order. | G6: 3 | H6: S1 | I6: US-202 | J6: Scenario: Edit quantity Given the cart contains 2 x "Chips Mayai" When the guest changes quantity to 3 Then line total and cart total update immediately Scenario: Add kitchen note When the guest types "No onions" in the item note Then the note is saved on the line and sent with the order Scenario: Cart survives page reload Given the cart has items When the guest reloads the page Then the cart is restored from local storage for the same session | K6: Not started
A7: US-204 | B7: E2 | C7: Must | D7: 6 | E7: Lounge Guest | F7: As a Lounge Guest, I want to submit my order and get instant confirmation so that I know the kitchen or bar has received it. | G7: 8 | H7: S1 | I7: US-203 | J7: Scenario: Successful submission Given the cart has valid items and an active session When the guest taps "Send order" Then an order with status "NEW" is created And the KDS shows a ticket within 2 seconds at p95 And the guest sees an order number and estimated status Scenario: Duplicate tap or retry is idempotent Given the guest taps "Send order" twice with the same client_order_id Then only one order exists And both responses return the same order id Scenario: Price changed since page load Given a menu price changed after the guest loaded the menu When the guest submits the order Then the server re-prices items from current menu data And the guest is shown the updated total before confirming | K7: Not started
A8: US-506 | B8: E5 | C8: Must | D8: 7 | E8: Venue Manager | F8: As a Venue Manager, I want staff to sign in with roles (waiter, kitchen, manager) using a simple PIN or password so that the right people see the right screens. | G8: 5 | H8: S1 | J8: Scenario: Staff login When a staff member enters a valid venue code and PIN Then a short-lived token is issued with their role Scenario: Role restriction Given a kitchen user When they request manager reports Then the API returns 403 Scenario: Lockout When 5 wrong PINs are entered within 10 minutes Then the account is locked for 15 minutes | K8: Not started
A9: US-601 | B9: E6 | C9: Must | D9: 8 | E9: Venue Manager | F9: As a Venue Manager, I want to manage categories, items, prices, photos and modifiers so that the menu always reflects what we sell. | G9: 8 | H9: S1 | J9: Scenario: Create item with modifier group When the manager saves a new item with a modifier group Then the item appears in the guest menu within 1 minute Scenario: Image optimisation When a photo larger than 1 MB is uploaded Then it is resized and served as WebP/AVIF with a width-appropriate variant Scenario: Bulk import When the manager uploads a valid CSV Then items are created and errors are listed per row | K9: Not started
A10: US-602 | B10: E6 | C10: Must | D10: 9 | E10: Venue Manager | F10: As a Venue Manager, I want to create tables and download a print-ready QR sticker sheet so that I can set up without technical help. | G10: 5 | H10: S1 | J10: Scenario: Generate QR codes Given the manager adds tables "T1" to "T14" When they click "Download QR stickers" Then a PDF is produced with one signed QR per table, table label and venue name Scenario: Regenerate compromised QR When the manager rotates a table QR token Then the old QR stops working immediately | K10: Not started
A11: US-701 | B11: E7 | C11: Must | D11: 10 | E11: Lounge Guest | F11: As a Lounge Guest, I want the app to load fast and work well on weak networks so that I do not abandon the page. | G11: 5 | H11: S1 | J11: Scenario: Performance budget in CI Given a pull request changes the guest PWA When CI runs Lighthouse with Fast 3G and 4x CPU throttling Then the build fails if LCP exceeds 4.0 seconds or initial JS exceeds 150 KB gzipped Scenario: Repeat visits Given the service worker has cached the app shell and menu When the guest reopens the page Then the shell renders in 1.5 seconds or less and the menu is revalidated in the background | K11: Not started
A12: US-301 | B12: E3 | C12: Must | D12: 11 | E12: Lounge Guest | F12: As a Lounge Guest, I want to see the full table bill with line items, service charge and tax so that I understand exactly what we owe. | G12: 5 | H12: S2 | I12: US-204 | J12: Scenario: Bill aggregates all non-rejected order lines Given a session with 3 orders When the guest opens the bill Then all non-rejected lines are listed with quantities and modifier prices And the subtotal, service charge, tax and total are shown in TZS Scenario: Bill updates when new orders arrive Given the bill page is open When another guest at the table submits an order Then the bill updates within 3 seconds | K12: Not started
A13: US-302 | B13: E3 | C13: Must | D13: 12 | E13: Lounge Guest | F13: As a Lounge Guest, I want to split the bill equally among N guests so that everyone pays the same amount without calculators. | G13: 5 | H13: S2 | I13: US-301 | J13: Scenario: Even split Given a bill total of 90,000 TZS When the guest selects Equal split with 3 payers Then 3 shares of 30,000 TZS are created Scenario: Remainder handled deterministically Given a bill total of 100,000 TZS and 3 payers When the split is calculated Then shares are 33,334, 33,333 and 33,333 TZS And the shares sum exactly to the bill total Scenario: Invalid payer count When the guest enters 0 or more payers than the maximum allowed Then the split is rejected with a validation message | K13: Not started
A14: US-303 | B14: E3 | C14: Must | D14: 13 | E14: Lounge Guest | F14: As a Lounge Guest, I want to pay only for the items I ordered or ate so that I do not subsidise others. | G14: 8 | H14: S2 | I14: US-301 | J14: Scenario: Claim items Given a bill with items ordered by different guests When Guest A selects the items she consumed Then Guest A’s share equals those items plus proportional service charge and tax Scenario: Item cannot be claimed twice (unless shared) Given an item is fully claimed by Guest A When Guest B tries to claim it Then the claim is rejected as "ALREADY_CLAIMED" Scenario: Unclaimed items remain visible Given some items are unclaimed Then the screen shows "Unassigned: X TZS" And the split cannot be locked until the unassigned amount is zero or reassigned | K14: Not started
A15: US-305 | B15: E3 | C15: Must | D15: 14 | E15: Lounge Guest | F15: As a Lounge Guest, I want to lock the split before paying so that the amounts cannot change while payment prompts are in progress. | G15: 8 | H15: S2 | I15: US-302 | J15: Scenario: Lock a valid split Given all items are assigned and shares sum to the bill total When the guest taps "Confirm split" Then the split status becomes "LOCKED" with an expiry of 10 minutes And new orders on the session are held as a separate pending bill Scenario: Concurrent modification is prevented Given two guests try to lock different splits at the same time Then exactly one split is locked And the other receives 409 "SPLIT_ALREADY_LOCKED" Scenario: Lock expires with no payments Given a locked split has no initiated payments When the lock expires Then the split reverts to "OPEN" And payments in progress prevent expiry until resolved | K15: Not started
A16: US-401 | B16: E4 | C16: Must | D16: 15 | E16: Lounge Guest | F16: As a Lounge Guest, I want to pay my share by mobile money push prompt so that I can pay from my own phone without leaving the page. | G16: 8 | H16: S2 | I16: US-305 | J16: Scenario: Initiate payment Given my share is 30,000 TZS and the split is LOCKED When I choose "M-Pesa", enter a valid phone number and tap "Pay" Then a payment transaction is created with status "PENDING" And a push prompt is requested from the provider And the screen shows "Check your phone and enter your PIN" Scenario: Invalid phone number When the phone number does not match the selected provider format Then the request is blocked with an inline message Scenario: Duplicate pay request Given a PENDING transaction exists for my share When I tap "Pay" again with the same idempotency key Then no second prompt is sent and the existing transaction is returned | K16: Not started
A17: US-501 | B17: E5 | C17: Must | D17: 16 | E17: Kitchen / Bar Staff | F17: As a Kitchen / Bar Staff, I want a real-time ticket queue with a clear alert for new orders so that no order is missed during rush hour. | G17: 8 | H17: S2 | I17: US-204 | J17: Scenario: New ticket appears Given the KDS is open for station "Kitchen" When a guest submits an order containing kitchen items Then a new ticket appears at the top within 2 seconds at p95 And an audible and visual alert is triggered Scenario: Ticket contents Then the ticket shows table, time since order, items, modifiers and notes Scenario: Late ticket highlighting Given a ticket is older than 10 minutes Then it is highlighted in amber, and in red after 15 minutes | K17: Not started
A18: US-502 | B18: E5 | C18: Must | D18: 17 | E18: Kitchen / Bar Staff | F18: As a Kitchen / Bar Staff, I want to move tickets through states with one tap so that guests and waiters can see accurate progress. | G18: 8 | H18: S2 | I18: US-501 | J18: Scenario: Valid transition Given a ticket is "NEW" When staff tap "Accept" Then status becomes "ACCEPTED" and the guest and waiter views update Scenario: Allowed sequence Then allowed transitions are NEW -> ACCEPTED -> PREPARING -> READY -> SERVED And an invalid jump returns 409 "INVALID_TRANSITION" Scenario: Reject item with reason When staff reject an item with a reason Then item status is "REJECTED", the bill is adjusted and the waiter is alerted Scenario: Two devices act at once Given two KDS devices tap the same ticket Then the first transition wins and the second shows the current state | K18: Not started
A19: US-504 | B19: E5 | C19: Must | D19: 18 | E19: Waiter | F19: As a Waiter, I want a table dashboard showing orders and payment status per table and per guest share so that I know where to go and who has paid. | G19: 8 | H19: S2 | I19: US-501 | J19: Scenario: Table cards When the waiter opens the dashboard Then each active table shows status, open balance and number of shares paid Scenario: Payment update When a guest payment succeeds Then the table card updates within 2 seconds Scenario: Ready items alert When items become READY Then the waiter sees an alert with table and items | K19: Not started
A20: US-205 | B20: E2 | C20: Must | D20: 19 | E20: Waiter | F20: As a Waiter, I want to mark items sold out and have it reflect for guests in real time so that guests cannot order what we do not have. | G20: 3 | H20: S3 | I20: US-204 | J20: Scenario: Mark item unavailable Given item "Grilled Tilapia" is available When staff mark it unavailable Then connected guest menus show "Sold out" within 5 seconds Scenario: Order contains an item that just became unavailable Given the guest cart includes that item When the guest submits the order Then the server rejects that line with code "ITEM_UNAVAILABLE" And the guest can remove it and resubmit | K20: Not started
A21: US-206 | B21: E2 | C21: Must | D21: 20 | E21: Lounge Guest | F21: As a Lounge Guest, I want to see the live status of my order so that I know when to expect my food or drinks. | G21: 3 | H21: S3 | I21: US-502 | J21: Scenario: Status updates in real time Given an order is "NEW" When the kitchen changes it to "PREPARING" Then the guest page shows "Preparing" within 2 seconds Scenario: Rejected item When the kitchen rejects an item with reason "Out of stock" Then the guest sees the item marked and the bill total updates | K21: Not started
A22: US-402 | B22: E4 | C22: Must | D22: 21 | E22: Lounge Guest | F22: As a Lounge Guest, I want to see my payment status update in real time so that I know whether it succeeded without refreshing. | G22: 8 | H22: S3 | I22: US-401 | J22: Scenario: Successful callback Given a transaction is "PENDING" When the provider webhook reports success with a valid signature Then the transaction becomes "SUCCESS" exactly once And the share becomes "PAID" And the guest page shows "Payment received" within 2 seconds Scenario: Duplicate webhook delivery When the same provider event is delivered twice Then the second is acknowledged but causes no state change Scenario: Invalid signature When a webhook arrives with an invalid signature Then the API returns 401 and logs a security event | K22: Not started
A23: US-403 | B23: E4 | C23: Must | D23: 22 | E23: Lounge Guest | F23: As a Lounge Guest, I want clear handling of failed, cancelled or expired payments, with retry so that I can complete payment even if the first attempt fails. | G23: 5 | H23: S3 | I23: US-402 | J23: Scenario: Insufficient funds When the provider reports "INSUFFICIENT_FUNDS" Then the transaction becomes "FAILED" with a user-friendly reason And the guest can retry or switch provider Scenario: Prompt not answered Given a transaction remains PENDING for 120 seconds Then the screen offers "Resend prompt" and "Choose another method" Scenario: Retry creates a new attempt Then the new attempt references the same share and the old one stays recorded as FAILED | K23: Not started
... A27: US-505 | B27: E5 | C27: Must | D27: 26 | E27: Waiter | F27: As a Waiter, I want the dashboard and KDS to recover automatically after a network drop so that I never miss orders because of Wi-Fi problems. | G27: 8 | H27: S3 | I27: US-501 | J27: Scenario: Reconnect and resync Given the KDS loses connection for 60 seconds When it reconnects Then it requests events since its last sequence number And any missed tickets are shown without a page reload Scenario: Offline banner When connection is lost Then a visible "Offline - reconnecting" banner appears And actions are queued or disabled with a clear message Scenario: Fallback transport When WebSocket connection fails repeatedly Then the client falls back to polling every 5 seconds | K27: Not started
A28: US-702 | B28: E7 | C28: Must | D28: 27 | E28: Tech Lead | F28: As a Tech Lead, I want logging, metrics and alerts across API, real-time and payment flows so that we detect failures before venues complain. | G28: 5 | H28: S3 | J28: Scenario: Payment anomaly alert When more than 5 payment callbacks fail processing in 5 minutes Then an alert is sent to the on-call channel Scenario: Trace an order Given an order id Then logs and traces across API, queue and websocket delivery can be found using one correlation id | K28: Not started
A29: US-703 | B29: E7 | C29: Must | D29: 28 | E29: Tech Lead | F29: As a Tech Lead, I want rate limiting, input validation and webhook authenticity checks so that the platform resists abuse and fraud. | G29: 5 | H29: S3 | J29: Scenario: Rate limit session creation When one IP exceeds 30 session-init requests per minute Then further requests receive 429 with Retry-After Scenario: Webhook IP and signature allow-listing When a callback comes from a non-allow-listed source or has a bad signature Then it is rejected and logged Scenario: Guest cannot access another session Given a valid token for session A When the guest requests data of session B Then the API returns 403 | K29: Not started
A30: US-103 | B30: E1 | C30: Should | D30: 29 | E30: Venue Manager | F30: As a Venue Manager, I want sessions to close automatically after the table is fully paid or has been idle too long so that old sessions cannot be used by someone who scans a QR code later. | G30: 3 | H30: S4 | I30: US-101 | J30: Scenario: Session closes after full payment Given all bill shares in the session are "PAID" When the final payment is confirmed Then the session status becomes "CLOSED" And participants receive a "session.closed" event Scenario: Idle timeout Given a session has had no activity for the venue-configured idle period And the bill has an outstanding balance of 0 When the cleanup job runs Then the session is closed Scenario: Scan after closure Given session S1 for "T12" is "CLOSED" When a new guest scans the "T12" QR code Then a new session is created and S1 data is not visible | K30: Not started
A31: US-104 | B31: E1 | C31: Should | D31: 30 | E31: Waiter | F31: As a Waiter, I want to open, move or close a table session from my dashboard so that I can fix situations such as guests changing tables or a QR scanned by mistake. | G31: 3 | H31: S4 | I31: US-504 | J31: Scenario: Waiter closes a session with zero balance Given a session with outstanding balance 0 When the waiter taps "Close table" Then the session status becomes "CLOSED" Scenario: Waiter cannot close an unpaid session without a reason Given a session with outstanding balance greater than 0 When the waiter taps "Close table" Then a confirmation asks for a reason (cash paid, comped, walked out) And the reason is stored in the audit log Scenario: Move session to another table Given a session on "T12" and table "T15" has no active session When the waiter moves the session to "T15" Then guests see the new table name and no data is lost | K31: Not started
A32: US-304 | B32: E3 | C32: Should | D32: 31 | E32: Lounge Guest | F32: As a Lounge Guest, I want to share items such as a platter or bottle among selected friends so that shared orders are split fairly. | G32: 5 | H32: S4 | I32: US-303 | J32: Scenario: Share one item among three guests Given an item priced 60,000 TZS When it is shared among 3 selected guests Then each guest is allocated 20,000 TZS of the item Scenario: Rounding on shared item Given an item priced 10,000 TZS shared among 3 guests Then allocations are 3,334, 3,333 and 3,333 TZS And the sum equals the item price | K32: Not started
A33: US-406 | B33: E4 | C33: Should | D33: 32 | E33: Waiter | F33: As a Waiter, I want to record a cash payment for a share so that guests who prefer cash can still use the split flow. | G33: 3 | H33: S4 | I33: US-504 | J33: Scenario: Mark share as paid by cash Given an unpaid share When the waiter marks it "Paid in cash" Then the share becomes PAID with method "CASH" and the waiter id is logged | K33: Not started
A34: US-503 | B34: E5 | C34: Should | D34: 33 | E34: Kitchen / Bar Staff | F34: As a Kitchen / Bar Staff, I want orders to be routed to the right station (kitchen vs bar) so that each station sees only its items. | G34: 5 | H34: S4 | I34: US-501 | J34: Scenario: Mixed order is split by station Given an order has 1 grill item and 2 drinks Then the kitchen KDS shows the grill item and the bar KDS shows the drinks And the waiter sees combined order progress | K34: Not started
A35: US-603 | B35: E6 | C35: Should | D35: 34 | E35: Venue Manager | F35: As a Venue Manager, I want a daily summary of sales and payments by method so that I can reconcile at close without manual work. | G35: 5 | H35: S4 | I35: US-402 | J35: Scenario: Daily summary When the manager opens "Today" Then totals by payment method, number of orders and unsettled tables are shown Scenario: Export When the manager taps export Then a CSV for the selected date range is downloaded | K35: Not started
A36: US-604 | B36: E6 | C36: Should | D36: 35 | E36: Venue Owner | F36: As a Venue Owner, I want to sign up my venue and manage my subscription so that I can onboard without waiting on the Cloud-Menu team. | G36: 5 | H36: S4 | J36: Scenario: Venue sign-up When an owner completes the sign-up form Then a venue is created in "TRIAL" status with a default table and sample menu Scenario: Suspension When a subscription is overdue by the configured grace period Then the venue status becomes "SUSPENDED" and guests see the unavailable page | K36: Not started
A37: US-207 | B37: E2 | C37: Could | D37: 36 | E37: Lounge Guest | F37: As a Lounge Guest, I want to call a waiter from my phone so that I can get help without waving. | G37: 2 | H37: S4 | I37: US-504 | J37: Scenario: Call waiter When the guest taps "Call waiter" Then the waiter dashboard shows an alert for the table And repeated taps within 60 seconds are ignored | K37: Not started
A38: US-306 | B38: E3 | C38: Could | D38: 37 | E38: Lounge Guest | F38: As a Lounge Guest, I want to add an optional tip to my share so that I can reward good service. | G38: 3 | H38: S4 | I38: US-305 | J38: Scenario: Add tip When the guest adds a 10% tip to their share Then the payable amount increases and the tip is recorded separately from the bill | K38: Not started

Sheet Sprint Summary
A1: Sprint | B1: Weeks | C1: Stories | D1: Points | E1: Must pts | F1: Should pts | G1: Could pts | H1: Focus
A2: S1 | B2: 1-2 | C2: =COUNTIF(Backlog!$H$2:$H$200,A2) -> 10 | D2: =SUMIFS(Backlog!$G$2:$G$200,Backlog!$H$2:$H$200,A2) -> 55 | E2: =SUMIFS(Backlog!$G$2:$G$200,Backlog!$H$2:$H$200,$A2,Backlog!$C$2:$C$200,"Must") -> 55 | F2: =SUMIFS(Backlog!$G$2:$G$200,Backlog!$H$2:$H$200,$A2,Backlog!$C$2:$C$200,"Should") -> 0 | G2: =SUMIFS(Backlog!$G$2:$G$200,Backlog!$H$2:$H$200,$A2,Backlog!$C$2:$C$200,"Could") -> 0 | H2: Foundation: QR/session, menu, modifiers, cart, order submit, staff auth, menu admin, QR stickers, performance budget
A3: S2 | B3: 3-4 | C3: =COUNTIF(Backlog!$H$2:$H$200,A3) -> 8 | D3: =SUMIFS(Backlog!$G$2:$G$200,Backlog!$H$2:$H$200,A3) -> 58 | E3: =SUMIFS(Backlog!$G$2:$G$200,Backlog!$H$2:$H$200,$A3,Backlog!$C$2:$C$200,"Must") -> 58 | F3: =SUMIFS(Backlog!$G$2:$G$200,Backlog!$H$2:$H$200,$A3,Backlog!$C$2:$C$200,"Should") -> 0 | G3: =SUMIFS(Backlog!$G$2:$G$200,Backlog!$H$2:$H$200,$A3,Backlog!$C$2:$C$200,"Could") -> 0 | H3: Real-time ops and splitting: KDS, waiter dashboard, bill, equal/itemized split, split lock, payment initiation
A4: S3 | B4: 5-6 | C4: =COUNTIF(Backlog!$H$2:$H$200,A4) -> 10 | D4: =SUMIFS(Backlog!$G$2:$G$200,Backlog!$H$2:$H$200,A4) -> 55 | E4: =SUMIFS(Backlog!$G$2:$G$200,Backlog!$H$2:$H$200,$A4,Backlog!$C$2:$C$200,"Must") -> 55 | F4: =SUMIFS(Backlog!$G$2:$G$200,Backlog!$H$2:$H$200,$A4,Backlog!$C$2:$C$200,"Should") -> 0 | G4: =SUMIFS(Backlog!$G$2:$G$200,Backlog!$H$2:$H$200,$A4,Backlog!$C$2:$C$200,"Could") -> 0 | H4: Payments hardening: webhooks, retries, reconciliation, receipts, reconnect/resync, security, observability
A5: S4 | B5: 7-8 | C5: =COUNTIF(Backlog!$H$2:$H$200,A5) -> 9 | D5: =SUMIFS(Backlog!$G$2:$G$200,Backlog!$H$2:$H$200,A5) -> 34 | E5: =SUMIFS(Backlog!$G$2:$G$200,Backlog!$H$2:$H$200,$A5,Backlog!$C$2:$C$200,"Must") -> 0 | F5: =SUMIFS(Backlog!$G$2:$G$200,Backlog!$H$2:$H$200,$A5,Backlog!$C$2:$C$200,"Should") -> 29 | G5: =SUMIFS(Backlog!$G$2:$G$200,Backlog!$H$2:$H$200,$A5,Backlog!$C$2:$C$200,"Could") -> 5 | H5: Polish and launch: session lifecycle, cash payments, routing, reporting, subscription, beta rollout
A6: Total | C6: =SUM(C2:C5) -> 37 | D6: =SUM(D2:D5) -> 202 | E6: =SUM(E2:E5) -> 168 | F6: =SUM(F2:F5) -> 29 | G6: =SUM(G2:G5) -> 5
A8: Note: capacity assumes a team of about 3-4 engineers plus part-time design/QA. Re-baseline velocity after Sprint 1.

Sheet Definition of Ready
A1: Area | B1: Checklist item | C1: Done?
A2: Clarity | B2: Story follows "As a / I want / so that" and is understood by the whole team | C2: ☐
A3: Clarity | B3: Acceptance criteria written in Given/When/Then, including at least one negative or error scenario | C3: ☐
A4: Clarity | B4: Dependencies identified and unblocked (or scheduled earlier) | C4: ☐
A5: Design & UX | B5: Mobile-first wireframe or mock available for any UI change (360 px width baseline) | C5: ☐
A6: Design & UX | B6: Copy for empty, loading and error states drafted (English and Swahili where guest-facing) | C6: ☐
A7: Design & UX | B7: Touch targets 44 px or larger and contrast requirements noted | C7: ☐
A8: Performance | B8: Performance impact assessed (bundle size, API calls, image weight) and budget noted | C8: ☐
A9: Performance | B9: Behaviour on slow or dropped networks described (retry, offline message, caching) | C9: ☐
A10: Security & data | B10: Data touched is listed; personal data (phone numbers) minimised and retention noted | C10: ☐
A11: Security & data | B11: Authorisation rules stated (guest session, staff role, manager) | C11: ☐
A12: Security & data | B12: Payment-related stories list idempotency and webhook considerations | C12: ☐
... A15: Estimate & test | B15: Product Owner has confirmed priority and value | C15: ☐

Sheet Definition of Done
A1: Area | B1: Checklist item | C1: Done?
A2: Code quality | B2: Code reviewed by at least one peer and merged to main through CI | C2: ☐
A3: Code quality | B3: Unit and integration tests written; critical flows covered; CI green | C3: ☐
A4: Code quality | B4: No new critical or high static-analysis or dependency vulnerabilities | C4: ☐
A5: Functional | B5: All Gherkin acceptance criteria demonstrated on staging and passed | C5: ☐
A6: Functional | B6: Automated end-to-end test added for money, split and order-state flows | C6: ☐
A7: Functional | B7: Product Owner accepted the story in sprint review | C7: ☐
A8: Web performance | B8: Lighthouse CI passes on Fast 3G / 4x CPU: LCP at most 4.0 s (3G) and 2.5 s (4G profile) | C8: ☐
A9: Web performance | B9: Guest PWA initial JavaScript at most 150 KB gzipped; images responsive and in modern formats | C9: ☐
A10: Web performance | B10: Service worker caching verified; repeat load at most 1.5 s | C10: ☐
A11: Web performance | B11: Real-time reconnect tested with network drops (offline banner, resync works) | C11: ☐
A12: Mobile UX | B12: Verified on the device matrix (low-end and mid-range Android, iOS Safari, Chrome) | C12: ☐
... A22: Operations | B22: Runbook or docs updated; feature flag in place for risky changes | C22: ☐
